{"table_name": "lineitem", "rows": 29999795, "fields": [{"colName": "l_orderkey", "colType": "bigint", "uniqueValues": 7500000, "minValue": 1, "maxValue": 30000000}, {"colName": "l_partkey", "colType": "bigint", "uniqueValues": 1000000, "minValue": 1, "maxValue": 1000000}, {"colName": "l_suppkey", "colType": "bigint", "uniqueValues": 50000, "minValue": 1, "maxValue": 50000}, {"colName": "l_linenumber", "colType": "int", "uniqueValues": 7, "minValue": 1, "maxValue": 7}, {"colName": "l_quantity", "colType": "decimal(18,2)", "uniqueValues": 50, "minValue": 1.0, "maxValue": 50.0}, {"colName": "l_extendedprice", "colType": "decimal(18,2)", "uniqueValues": 1124790, "minValue": 900.99, "maxValue": 104949.5}, {"colName": "l_discount", "colType": "decimal(18,2)", "uniqueValues": 11, "minValue": 0.0, "maxValue": 0.1}, {"colName": "l_tax", "colType": "decimal(18,2)", "uniqueValues": 9, "minValue": 0.0, "maxValue": 0.08}, {"colName": "l_returnflag", "colType": "string", "uniqueValues": 3, "values": ["A", "N", "R"], "weights": [25.0, 51.0, 25.0]}, {"colName": "l_linestatus", "colType": "string", "uniqueValues": 2, "values": ["F", "O"], "weights": [50.0, 50.0]}, {"colName": "l_shipdate", "colType": "date", "uniqueValues": 2526, "begin": "1992-01-02", "end": "1998-12-01"}, {"colName": "l_commitdate", "colType": "date", "uniqueValues": 2466, "begin": "1992-01-31", "end": "1998-10-31"}, {"colName": "l_receiptdate", "colType": "date", "uniqueValues": 2555, "begin": "1992-01-03", "end": "1998-12-31"}, {"colName": "l_shipinstruct", "colType": "string", "uniqueValues": 4, "values": ["TAKE BACK RETURN", "COLLECT COD", "NONE", "DELIVER IN PERSON"], "weights": [25.0, 25.0, 25.0, 25.0]}, {"colName": "l_shipmode", "colType": "string", "uniqueValues": 7, "values": ["AIR", "MAIL", "RAIL", "SHIP", "TRUCK", "REG AIR", "FOB"], "weights": [14.0, 14.0, 14.0, 14.0, 14.0, 14.0, 14.0]}, {"colName": "l_comment", "colType": "string", "uniqueValues": 19191446, "template": "\\w"}]}